Proyecto1/ALU/ALU_Substractor.sv
// ALU_Substractor
// Entradas: piso_init (piso actual), pisos_bajar
// Salidas:  A_minus1, A_eq_min, B_restantes

// Saturacion inferior: si pisos_bajar > piso_init
//   B_restantes = piso_init  (solo baja lo que puede)

module ALU_Substractor (
    input  [3:0] piso_init,
    input  [3:0] pisos_bajar,
    input  [3:0] A_reg,
    output [3:0] A_minus1,
    output       A_eq_min,
    output [3:0] B_restantes
);

    // ----------------------------------------------------------------
    // A - 1 (borrow propagado)
    // ----------------------------------------------------------------
    wire d0, d1, d2;
    assign A_minus1[0] = A_reg[0] ^ 1'b1;
    assign d0           = ~A_reg[0];
    assign A_minus1[1] = A_reg[1] ^ d0;
    assign d1           = ~A_reg[1] & d0;
    assign A_minus1[2] = A_reg[2] ^ d1;
    assign d2           = ~A_reg[2] & d1;
    assign A_minus1[3] = A_reg[3] ^ d2;

    // ----------------------------------------------------------------
    // Saturacion A == 0000
    // ----------------------------------------------------------------
    assign A_eq_min = ~A_reg[3] & ~A_reg[2] & ~A_reg[1] & ~A_reg[0];

    // ----------------------------------------------------------------
    // Deteccion de underflow: piso_init - pisos_bajar
    // borrow propagado desde bit 0 hasta bit 3
    // Si borrow_3 sale del bit 3 → pisos_bajar > piso_init
    // ----------------------------------------------------------------
    wire [3:0] diff;
    wire       br0, br1, br2, br3;

    assign diff[0] = piso_init[0] ^ pisos_bajar[0];
    assign br0      = (~piso_init[0] & pisos_bajar[0]);

    assign diff[1] = piso_init[1] ^ pisos_bajar[1] ^ br0;
    assign br1      = (~piso_init[1] & pisos_bajar[1])
                    | (~piso_init[1] & br0)
                    | ( pisos_bajar[1] & br0);

    assign diff[2] = piso_init[2] ^ pisos_bajar[2] ^ br1;
    assign br2      = (~piso_init[2] & pisos_bajar[2])
                    | (~piso_init[2] & br1)
                    | ( pisos_bajar[2] & br1);

    assign diff[3] = piso_init[3] ^ pisos_bajar[3] ^ br2;
    assign br3      = (~piso_init[3] & pisos_bajar[3])
                    | (~piso_init[3] & br2)
                    | ( pisos_bajar[3] & br2);

    // br3 = 1 → underflow → B_restantes = piso_init
    // br3 = 0 → normal    → B_restantes = pisos_bajar
    assign B_restantes[0] = (br3 & piso_init[0]) | (~br3 & pisos_bajar[0]);
    assign B_restantes[1] = (br3 & piso_init[1]) | (~br3 & pisos_bajar[1]);
    assign B_restantes[2] = (br3 & piso_init[2]) | (~br3 & pisos_bajar[2]);
    assign B_restantes[3] = (br3 & piso_init[3]) | (~br3 & pisos_bajar[3]);

endmodule

ALU_Adder.sv
// ALU_Adder
// Entradas: piso_init, pisos_subir
// Salidas:  A_next, B_restantes 

// Saturacion superior: si piso_init + pisos_subir > 15
//   B_restantes = 15 - piso_init  (solo sube lo que puede)
// A_next = piso_init + 1 por ciclo mientras B != 0
// Saturacion de A: si A == 1111 no incrementa

module ALU_Adder (
    input  [3:0] piso_init,
    input  [3:0] pisos_subir,
    input  [3:0] A_reg,        // piso actual del registro
    output [3:0] A_plus1,      // A + 1 para el registro
    output       A_eq_max,     // A == 1111
    output [3:0] B_restantes    // pisos reales a recorrer (con saturacion)
);

    // ----------------------------------------------------------------
    // A + 1 (ripple-carry de 4 bits)
    // ----------------------------------------------------------------
    wire c0, c1, c2;
    assign A_plus1[0] = A_reg[0] ^ 1'b1;
    assign c0         = A_reg[0] & 1'b1;
    assign A_plus1[1] = A_reg[1] ^ c0;
    assign c1         = A_reg[1] & c0;
    assign A_plus1[2] = A_reg[2] ^ c1;
    assign c2         = A_reg[2] & c1;
    assign A_plus1[3] = A_reg[3] ^ c2;

    // ----------------------------------------------------------------
    // Saturacion A == 1111
    // ----------------------------------------------------------------
    assign A_eq_max = A_reg[3] & A_reg[2] & A_reg[1] & A_reg[0];

    // ----------------------------------------------------------------
    // Saturacion de entrada: piso_init + pisos_subir > 15?
    // pisos_disp = ~piso_init = 15 - piso_init
    // Si carry_up → desbordamiento → B_restantes = pisos_disp
    // ----------------------------------------------------------------
    wire [3:0] pisos_disp;
    assign pisos_disp[0] = ~piso_init[0];
    assign pisos_disp[1] = ~piso_init[1];
    assign pisos_disp[2] = ~piso_init[2];
    assign pisos_disp[3] = ~piso_init[3];

    wire [3:0] sum_check;
    wire       carry_up;
    wire       c_ab0, c_ab1, c_ab2;
    assign sum_check[0] = piso_init[0] ^ pisos_subir[0];
    assign c_ab0         = piso_init[0] & pisos_subir[0];
    assign sum_check[1] = piso_init[1] ^ pisos_subir[1] ^ c_ab0;
    assign c_ab1         = (piso_init[1] & pisos_subir[1])
                         | (piso_init[1] & c_ab0)
                         | (pisos_subir[1] & c_ab0);
    assign sum_check[2] = piso_init[2] ^ pisos_subir[2] ^ c_ab1;
    assign c_ab2         = (piso_init[2] & pisos_subir[2])
                         | (piso_init[2] & c_ab1)
                         | (pisos_subir[2] & c_ab1);
    assign sum_check[3] = piso_init[3] ^ pisos_subir[3] ^ c_ab2;
    assign carry_up      = (piso_init[3] & pisos_subir[3])
                         | (piso_init[3] & c_ab2)
                         | (pisos_subir[3] & c_ab2);

    assign B_restantes[0] = (carry_up & pisos_disp[0]) | (~carry_up & pisos_subir[0]);
    assign B_restantes[1] = (carry_up & pisos_disp[1]) | (~carry_up & pisos_subir[1]);
    assign B_restantes[2] = (carry_up & pisos_disp[2]) | (~carry_up & pisos_subir[2]);
    assign B_restantes[3] = (carry_up & pisos_disp[3]) | (~carry_up & pisos_subir[3]);

endmodule

Proyecto1/ALU/ALU.sv
// ALU: controlador estructural
// op = 0 --> subir (usa ALU_Adder)
// op = 1 --> bajar (usa ALU_Substractor)
// El timer interno genera un tick cada 1 segundo. En ese momento, A y B se actualizan

module ALU #(
    parameter integer CLK_FREQ = 50_000_000  // Hz (ESTO HAY QUE AJUSTARLO PARA LA IMPLENTACION REAL AL RELOJ DE LA FPGA)
)(
    input        clk,
    input        rst_n,
    input  [3:0] piso_init,
    input  [3:0] pisos_delta,  // pisos a subir o bajar
    input        load,
    input        op,           // 0 = subir, 1 = bajar
    output [3:0] piso_actual,
    output [2:0] pwm_level,
    output [6:0] seg,
    output       done          // 1 cuando se completo el ultimo ciclo
);

    // TIMER: cuenta ciclos de clk hasta CLK_FREQ para generar un tick cada 1 segundo
    localparam integer TIMER_MAX  = CLK_FREQ - 1;
    localparam integer TIMER_BITS = $clog2(CLK_FREQ);

    reg [TIMER_BITS-1:0] timer;

    // tick = 1 exactamente un ciclo cuando timer llega a TIMER_MAX
    wire tick;
    assign tick = (timer == TIMER_MAX);

    // timer + 1: sumador combinacional
    wire [TIMER_BITS-1:0] timer_inc;
    assign timer_inc = timer + 1'b1;

    // reset_timer = 1 cuando load o tick --> el timer vuelve a 0
    wire reset_timer;
    assign reset_timer = load | tick;

    // next_timer:
    //   Si reset_timer = 1  -->  next_timer = 0   (AND con 0 en cada bit)
    //   Si reset_timer = 0  -->  next_timer = timer_inc (AND con 1 en cada bit)
    wire [TIMER_BITS-1:0] next_timer;
    assign next_timer = {TIMER_BITS{~reset_timer}} & timer_inc;

    // Flip-flop del timer 
    always @(posedge clk or negedge rst_n) begin
        if (~rst_n) timer <= {TIMER_BITS{1'b0}};
        else        timer <= next_timer;
    end

    // ================================================================
    // REGISTROS A (piso actual) y B (pasos restantes)
    // ================================================================

    reg [3:0] A;
    reg [3:0] B;

    assign piso_actual = A;

    // ================================================================
    // INSTANCIAS ALU_Adder y ALU_Substractor
    // ================================================================

    wire [3:0] A_plus1;
    wire       A_eq_max;
    wire [3:0] B_ef_add;

    ALU_Adder adder (
        .piso_init   (piso_init),
        .pisos_subir (pisos_delta),
        .A_reg       (A),
        .A_plus1     (A_plus1),
        .A_eq_max    (A_eq_max),
        .B_restantes (B_ef_add)
    );

    wire [3:0] A_minus1;
    wire       A_eq_min;
    wire [3:0] B_ef_sub;

    ALU_Substractor substractor (
        .piso_init   (piso_init),
        .pisos_bajar (pisos_delta),
        .A_reg       (A),
        .A_minus1    (A_minus1),
        .A_eq_min    (A_eq_min),
        .B_restantes (B_ef_sub)
    );

    // ================================================================
    // MUX op: selecciona operacion subir/bajar
    // step_A    = A+1 si op=0, A-1 si op=1
    // B_restantes = B efectivos segun direccion
    // ================================================================

    wire [3:0] step_A;
    assign step_A[0] = (~op & A_plus1[0]) | (op & A_minus1[0]);
    assign step_A[1] = (~op & A_plus1[1]) | (op & A_minus1[1]);
    assign step_A[2] = (~op & A_plus1[2]) | (op & A_minus1[2]);
    assign step_A[3] = (~op & A_plus1[3]) | (op & A_minus1[3]);

    wire [3:0] B_restantes;
    assign B_restantes[0] = (~op & B_ef_add[0]) | (op & B_ef_sub[0]);
    assign B_restantes[1] = (~op & B_ef_add[1]) | (op & B_ef_sub[1]);
    assign B_restantes[2] = (~op & B_ef_add[2]) | (op & B_ef_sub[2]);
    assign B_restantes[3] = (~op & B_ef_add[3]) | (op & B_ef_sub[3]);

    // ================================================================
    // enable: B != 0   (el ascensor aun tiene pasos por dar)
    // hold_A: A no debe moverse (B agotado o saturacion de piso)
    // ================================================================

    wire enable;
    assign enable = B[3] | B[2] | B[1] | B[0];

    wire hold_A;
    assign hold_A = (~enable)
                  | (~op & enable & A_eq_max)
                  | ( op & enable & A_eq_min);

    // ================================================================
    // B - 1: restador combinacional (ripple borrow)
    // ================================================================

    wire [3:0] B_minus1;
    wire bw0, bw1, bw2;
    assign B_minus1[0] = B[0] ^ 1'b1;
    assign bw0          = ~B[0];
    assign B_minus1[1] = B[1] ^ bw0;
    assign bw1          = ~B[1] & bw0;
    assign B_minus1[2] = B[2] ^ bw1;
    assign bw2          = ~B[2] & bw1;
    assign B_minus1[3] = B[3] ^ bw2;


    // update: A y B solo cambian cuando hay tick o load (Ecuacion booleana: update = load | tick)
    wire update;
    assign update = load | tick;

    // ================================================================
    // A_comb: valor de A si ocurre una actualizacion (load o tick)
    //
    // Tabla de verdad del MUX:
    //   load=1              --> A_comb = piso_init
    //   load=0, hold_A=1    --> A_comb = A  (saturacion o B==0)
    //   load=0, hold_A=0    --> A_comb = step_A  (avanza un piso)
    // ================================================================

    wire [3:0] A_comb;
    assign A_comb[0] = (load & piso_init[0])
                     | (~load & ~hold_A & step_A[0])
                     | (~load &  hold_A & A[0]);
    assign A_comb[1] = (load & piso_init[1])
                     | (~load & ~hold_A & step_A[1])
                     | (~load &  hold_A & A[1]);
    assign A_comb[2] = (load & piso_init[2])
                     | (~load & ~hold_A & step_A[2])
                     | (~load &  hold_A & A[2]);
    assign A_comb[3] = (load & piso_init[3])
                     | (~load & ~hold_A & step_A[3])
                     | (~load &  hold_A & A[3]);

    // next_A: A_comb si hay actualizacion; A sin cambio si no next_A[i] = (update & A_comb[i]) | (~update & A[i])
    wire [3:0] next_A;
    assign next_A[0] = (update & A_comb[0]) | (~update & A[0]);
    assign next_A[1] = (update & A_comb[1]) | (~update & A[1]);
    assign next_A[2] = (update & A_comb[2]) | (~update & A[2]);
    assign next_A[3] = (update & A_comb[3]) | (~update & A[3]);

    // ================================================================
    // B_comb: valor de B si ocurre una actualizacion (load o tick)
    //
    //   load=1              --> B_comb = B_restantes  (carga el delta)
    //   load=0, enable=1    --> B_comb = B - 1
    //   load=0, enable=0    --> B_comb = B  (ya es 0, no cambia)
    // ================================================================

    wire [3:0] B_comb;
    assign B_comb[0] = (load  &  B_restantes[0])
                     | (~load &  enable  & B_minus1[0])
                     | (~load & ~enable  & B[0]);
    assign B_comb[1] = (load  &  B_restantes[1])
                     | (~load &  enable  & B_minus1[1])
                     | (~load & ~enable  & B[1]);
    assign B_comb[2] = (load  &  B_restantes[2])
                     | (~load &  enable  & B_minus1[2])
                     | (~load & ~enable  & B[2]);
    assign B_comb[3] = (load  &  B_restantes[3])
                     | (~load &  enable  & B_minus1[3])
                     | (~load & ~enable  & B[3]);

    // next_B: B_comb si hay actualizacion; B sin cambio si no next_B[i] = (update & B_comb[i]) | (~update & B[i])
    wire [3:0] next_B;
    assign next_B[0] = (update & B_comb[0]) | (~update & B[0]);
    assign next_B[1] = (update & B_comb[1]) | (~update & B[1]);
    assign next_B[2] = (update & B_comb[2]) | (~update & B[2]);
    assign next_B[3] = (update & B_comb[3]) | (~update & B[3]);

    // Flip-flops de A y B — template minimo estructural
    always @(posedge clk or negedge rst_n) begin
        if (~rst_n) begin
            A <= 4'b0001;
            B <= 4'b0000;
        end else begin
            A <= next_A;
            B <= next_B;
        end
    end

    // ================================================================
    // FLAG active y OUTPUT done
    //
    // active: se activa con load y se mantiene hasta reset next_active = load | active
    // done = 1 cuando hubo al menos un load y B == 0 done = active & ~enable
    // ================================================================

    reg  active;
    wire next_active;
    assign next_active = load | active;

    // Flip-flop de active — template minimo estructural
    always @(posedge clk or negedge rst_n) begin
        if (~rst_n) active <= 1'b0;
        else        active <= next_active;
    end

    assign done = active & ~enable;

    // ================================================================
    // PWM LEVEL — 3 bits, ecuaciones booleanas
    // Tabla: B=0→000(0%) B=1→001(25%) B=2,3→010(50%)
    //        B=4→011(75%) B>=5→100(100%)
    // ================================================================

    wire B_ge5;
    assign B_ge5 = B[3] | (B[2] & B[1]) | (B[2] & B[0]);

    assign pwm_level[2] = B_ge5;
    assign pwm_level[1] = (~B[3] & ~B[2] &  B[1])
                        | (~B[3] &  B[2] & ~B[1] & ~B[0]);
    assign pwm_level[0] = (~B[3] & ~B[2] &  B[0])
                        | (~B[3] &  B[2] & ~B[1] & ~B[0]);

    // ================================================================
    // DECODER 7 SEGMENTOS {g,f,e,d,c,b,a} — ecuaciones booleanas
    // Muestra piso_actual (A) en hexadecimal: 0–F
    // ================================================================

    wire [6:0] seg_out;

    // Segmento a (seg_out[0]): apagado en 1 y 4
    assign seg_out[0] = ~(~A[3] & ~A[2] & ~A[1] &  A[0]) &
                        ~(~A[3] &  A[2] & ~A[1] & ~A[0]);

    // Segmento b (seg_out[1]): apagado en 5, 6, B, D
    assign seg_out[1] = ~(~A[3] & ~A[2] &  A[1] &  A[0]) &
                        ~(~A[3] &  A[2] &  A[1] & ~A[0]) &
                        ~( A[3] & ~A[2] &  A[1] &  A[0]) &
                        ~( A[3] &  A[2] &  A[1] & ~A[0]);

    // Segmento c (seg_out[2]): apagado en 2
    assign seg_out[2] = ~(~A[3] & ~A[2] &  A[1] & ~A[0]);

    // Segmento d (seg_out[3]): apagado en 1, 4, 7, A, F
    assign seg_out[3] = ~(~A[3] & ~A[2] & ~A[1] &  A[0]) &
                        ~(~A[3] &  A[2] & ~A[1] & ~A[0]) &
                        ~(~A[3] &  A[2] &  A[1] &  A[0]) &
                        ~( A[3] & ~A[2] &  A[1] & ~A[0]) &
                        ~( A[3] &  A[2] &  A[1] &  A[0]);

    // Segmento e (seg_out[4]): apagado en 1, 3, 4, 5, 7, 9
    assign seg_out[4] = ~(~A[3] & ~A[2] & ~A[1] &  A[0]) &
                        ~(~A[3] & ~A[2] &  A[1] &  A[0]) &
                        ~(~A[3] &  A[2] & ~A[1] & ~A[0]) &
                        ~(~A[3] &  A[2] & ~A[1] &  A[0]) &
                        ~(~A[3] &  A[2] &  A[1] &  A[0]) &
                        ~( A[3] & ~A[2] & ~A[1] &  A[0]);

    // Segmento f (seg_out[5]): apagado en 1, 2, 3, 7
    assign seg_out[5] = ~(~A[3] & ~A[2] & ~A[1] &  A[0]) &
                        ~(~A[3] & ~A[2] &  A[1] & ~A[0]) &
                        ~(~A[3] & ~A[2] &  A[1] &  A[0]) &
                        ~(~A[3] &  A[2] &  A[1] &  A[0]);

    // Segmento g (seg_out[6]): apagado en 0, 1, 7
    assign seg_out[6] = ~(~A[3] & ~A[2] & ~A[1] & ~A[0]) &
                        ~(~A[3] & ~A[2] & ~A[1] &  A[0]) &
                        ~(~A[3] &  A[2] &  A[1] &  A[0]);

    // Display de anodo comun: segmento activo = 0
    assign seg = ~seg_out;

endmodule

Proyecto1/ALU/ALU_tb.sv
`timescale 1ns/1ps

// Testbench para ALU con timer de 1 segundo y output 'done'
// CLK_FREQ=10 → tick cada 10 ciclos de clk = 100 ns (simulacion rapida)

module tb_alu_ascensor;
    reg        clk, rst_n, load, op;
    reg  [3:0] piso_init, pisos_delta;
    wire [6:0] seg;
    wire [3:0] piso_actual;
    wire [2:0] pwm_level;
    wire       done;

    // Instancia con CLK_FREQ pequeno para simulacion (tick cada 100 ns)
    ALU #(.CLK_FREQ(10)) dut (
        .clk(clk), .rst_n(rst_n),
        .piso_init(piso_init), .pisos_delta(pisos_delta),
        .load(load), .op(op),
        .piso_actual(piso_actual),
        .pwm_level(pwm_level),
        .seg(seg),
        .done(done)
    );

    always #5 clk = ~clk;

    function automatic [7:0] hex_char;
        input [3:0] val;
        case (val)
            4'h0: hex_char = "0";  4'h1: hex_char = "1";
            4'h2: hex_char = "2";  4'h3: hex_char = "3";
            4'h4: hex_char = "4";  4'h5: hex_char = "5";
            4'h6: hex_char = "6";  4'h7: hex_char = "7";
            4'h8: hex_char = "8";  4'h9: hex_char = "9";
            4'hA: hex_char = "A";  4'hB: hex_char = "B";
            4'hC: hex_char = "C";  4'hD: hex_char = "D";
            4'hE: hex_char = "E";  4'hF: hex_char = "F";
        endcase
    endfunction

    function automatic [6:0] pwm_pct;
        input [2:0] lvl;
        case (lvl)
            3'b000: pwm_pct = 7'd0;
            3'b001: pwm_pct = 7'd25;
            3'b010: pwm_pct = 7'd50;
            3'b011: pwm_pct = 7'd75;
            3'b100: pwm_pct = 7'd100;
            default: pwm_pct = 7'd0;
        endcase
    endfunction

    task automatic print_state;
        input [3:0] piso;
        input [2:0] lvl;
        input [6:0] segmentos;
        input       direccion;
        input       done_sig;
        reg [6:0] pct;
        reg [7:0] c;
        begin
            pct = pwm_pct(lvl);
            c   = hex_char(piso);
            $display("| Piso: %2d (hex: %s) | Dir: %s | PWM: %3d%% (%03b) | seg: %b | done: %b |",
                     piso, c,
                     direccion ? "BAJA" : "SUBE",
                     pct, lvl, segmentos, done_sig);
        end
    endtask

    // Imprime SOLO cuando piso_actual o done cambian (un estado por paso)
    // Evita la repeticion causada por el timer interno (CLK_FREQ ciclos por tick)
    reg [3:0] piso_prev;
    reg       done_prev;

    always @(posedge clk) begin
        if (~rst_n) begin
            piso_prev <= 4'hF;   // valor imposible para forzar primer print
            done_prev <= 1'b1;
        end else if (piso_actual !== piso_prev || done !== done_prev) begin
            print_state(piso_actual, pwm_level, seg, op, done);
            piso_prev <= piso_actual;
            done_prev <= done;
        end
    end

    // espera_ns como integer para soportar tiempos mayores
    task automatic do_test;
        input [3:0]  p_init;
        input [3:0]  p_delta;
        input        direccion;
        input [3:0]  esperado;
        input integer espera_ns;
        begin
            piso_init   = p_init;
            pisos_delta = p_delta;
            op          = direccion;
            #10 load = 1;
            #10 load = 0;
            #(espera_ns);
            $display("|----------------------------------------------------------------------|");
            $display("Resultado: %2d | Esperado: %2d | done: %b | %s\n",
                     piso_actual, esperado, done,
                     (piso_actual == esperado) ? "PASS" : "FAIL");
        end
    endtask

    initial begin
        $dumpfile("sim.vcd");
        $dumpvars(0, tb_alu_ascensor);

        clk = 0; rst_n = 0; load = 0; op = 0;
        piso_init = 0; pisos_delta = 0;
        #12 rst_n = 1;

        // Con CLK_FREQ=10 cada tick = 100 ns
        // Espera = pasos * 100 ns + 150 ns de margen

        // ==== SUBIR (op=0) ====
        $display("\n=== SUBE: piso 3 + 5 → esperado 8 (5 pasos x 100ns = 650ns total) ===");
        $display("|----------------------------------------------------------------------|");
        do_test(4'd3, 4'd5, 1'b0, 4'd8, 650);

        $display("=== SUBE: piso 13 + 5 → satura en 15 (B efectivo = 2, 350ns total) ===");
        $display("|----------------------------------------------------------------------|");
        do_test(4'd13, 4'd5, 1'b0, 4'd15, 350);

        $display("=== SUBE: piso 1 + 1 → piso 2 (1 paso, 250ns total) ===");
        $display("|----------------------------------------------------------------------|");
        do_test(4'd1, 4'd1, 1'b0, 4'd2, 250);

        $display("=== SUBE: piso 15 + 3 → ya en maximo (B efectivo = 0, done inmediato) ===");
        $display("|----------------------------------------------------------------------|");
        do_test(4'd15, 4'd3, 1'b0, 4'd15, 150);

        // ==== BAJAR (op=1) ====
        $display("=== BAJA: piso 10 - 5 → esperado 5 (5 pasos, 650ns total) ===");
        $display("|----------------------------------------------------------------------|");
        do_test(4'd10, 4'd5, 1'b1, 4'd5, 650);

        $display("=== BAJA: piso 3 - 5 → satura en 0 (B efectivo = 3, 450ns total) ===");
        $display("|----------------------------------------------------------------------|");
        do_test(4'd3, 4'd5, 1'b1, 4'd0, 450);

        $display("=== BAJA: piso 8 - 1 → piso 7 (1 paso, 250ns total) ===");
        $display("|----------------------------------------------------------------------|");
        do_test(4'd8, 4'd1, 1'b1, 4'd7, 250);

        $display("=== BAJA: piso 0 - 3 → ya en minimo (B efectivo = 0, done inmediato) ===");
        $display("|----------------------------------------------------------------------|");
        do_test(4'd0, 4'd3, 1'b1, 4'd0, 150);

        $finish;
    end

endmodule

Proyecto1/ALU/sim.vcd
$date
	Tue Mar 31 20:19:20 2026
$end
$version
	Icarus Verilog
$end
$timescale
	1ps
$end
$scope module tb_alu_ascensor $end
$var wire 7 ! seg [6:0] $end
$var wire 3 " pwm_level [2:0] $end
$var wire 4 # piso_actual [3:0] $end
$var wire 1 $ done $end
$var reg 1 % clk $end
$var reg 1 & done_prev $end
$var reg 1 ' load $end
$var reg 1 ( op $end
$var reg 4 ) piso_init [3:0] $end
$var reg 4 * piso_prev [3:0] $end
$var reg 4 + pisos_delta [3:0] $end
$var reg 1 , rst_n $end
$scope function hex_char $end
$upscope $end
$scope function pwm_pct $end
$upscope $end
$scope module dut $end
$var wire 1 - B_ge5 $end
$var wire 1 . bw0 $end
$var wire 1 / bw1 $end
$var wire 1 0 bw2 $end
$var wire 1 % clk $end
$var wire 1 $ done $end
$var wire 1 1 enable $end
$var wire 1 2 hold_A $end
$var wire 1 ' load $end
$var wire 1 3 next_active $end
$var wire 4 4 next_timer [3:0] $end
$var wire 1 ( op $end
$var wire 4 5 piso_actual [3:0] $end
$var wire 4 6 piso_init [3:0] $end
$var wire 4 7 pisos_delta [3:0] $end
$var wire 1 8 reset_timer $end
$var wire 1 , rst_n $end
$var wire 7 9 seg [6:0] $end
$var wire 1 : update $end
$var wire 4 ; timer_inc [3:0] $end
$var wire 1 < tick $end
$var wire 4 = step_A [3:0] $end
$var wire 7 > seg_out [6:0] $end
$var wire 3 ? pwm_level [2:0] $end
$var wire 4 @ next_B [3:0] $end
$var wire 4 A next_A [3:0] $end
$var wire 4 B B_restantes [3:0] $end
$var wire 4 C B_minus1 [3:0] $end
$var wire 4 D B_ef_sub [3:0] $end
$var wire 4 E B_ef_add [3:0] $end
$var wire 4 F B_comb [3:0] $end
$var wire 4 G A_plus1 [3:0] $end
$var wire 4 H A_minus1 [3:0] $end
$var wire 1 I A_eq_min $end
$var wire 1 J A_eq_max $end
$var wire 4 K A_comb [3:0] $end
$var parameter 32 L CLK_FREQ $end
$var parameter 32 M TIMER_BITS $end
$var parameter 32 N TIMER_MAX $end
$var reg 4 O A [3:0] $end
$var reg 4 P B [3:0] $end
$var reg 1 Q active $end
$var reg 4 R timer [3:0] $end
$scope module adder $end
$var wire 1 J A_eq_max $end
$var wire 4 S A_reg [3:0] $end
$var wire 1 T c0 $end
$var wire 1 U c1 $end
$var wire 1 V c2 $end
$var wire 1 W c_ab0 $end
$var wire 1 X c_ab1 $end
$var wire 1 Y c_ab2 $end
$var wire 1 Z carry_up $end
$var wire 4 [ piso_init [3:0] $end
$var wire 4 \ pisos_subir [3:0] $end
$var wire 4 ] sum_check [3:0] $end
$var wire 4 ^ pisos_disp [3:0] $end
$var wire 4 _ B_restantes [3:0] $end
$var wire 4 ` A_plus1 [3:0] $end
$upscope $end
$scope module substractor $end
$var wire 1 I A_eq_min $end
$var wire 4 a A_reg [3:0] $end
$var wire 1 b br0 $end
$var wire 1 c br1 $end
$var wire 1 d br2 $end
$var wire 1 e br3 $end
$var wire 1 f d0 $end
$var wire 1 g d1 $end
$var wire 1 h d2 $end
$var wire 4 i piso_init [3:0] $end
$var wire 4 j pisos_bajar [3:0] $end
$var wire 4 k diff [3:0] $end
$var wire 4 l B_restantes [3:0] $end
$var wire 4 m A_minus1 [3:0] $end
$upscope $end
$upscope $end
$scope task do_test $end
$upscope $end
$scope task print_state $end
$upscope $end
$upscope $end
$enddefinitions $end
$comment Show the parameter values. $end
$dumpall
b1001 N
b100 M
b1010 L
$end
#0
$dumpvars
b0 m
b0 l
b0 k
b0 j
b0 i
0h
0g
0f
0e
0d
0c
0b
b1 a
b10 `
b0 _
b1111 ^
b0 ]
b0 \
b0 [
0Z
0Y
0X
0W
0V
0U
1T
b1 S
b0 R
0Q
b0 P
b1 O
b1 K
0J
0I
b0 H
b10 G
b0 F
b0 E
b0 D
b1111 C
b0 B
b1 A
b0 @
b0 ?
b110 >
b10 =
0<
b1 ;
0:
b1111001 9
08
b0 7
b0 6
b1 5
b1 4
03
12
01
10
1/
1.
0-
0,
b0 +
bx *
b0 )
0(
0'
x&
0%
0$
b1 #
b0 "
b1111001 !
$end
#5000
1&
b1111 *
1%
#10000
0%
#12000
b101 B
1e
1Y
1X
b1000 ]
b101 E
b101 _
1d
b11 D
b11 l
b1110 k
b1100 ^
1W
b101 +
b101 7
b101 \
b101 j
b11 )
b11 6
b11 [
b11 i
1,
#15000
b10 4
b10 ;
b1 R
0&
b1 *
1%
#20000
0%
#22000
b11 A
b101 @
b11 K
b101 F
b0 4
18
1:
13
1'
#25000
b110010 !
b110010 9
b1001101 >
b100 =
02
b100 "
b100 ?
0/
b100 C
00
1-
b100 G
b100 `
b10 H
b10 m
11
0.
1U
0$
1Q
b101 P
b11 #
b11 5
b11 O
b11 S
b11 a
b1 ;
b0 R
1%
#30000
0%
#32000
b100 K
b100 F
b1 4
08
0:
0'
#35000
b10 4
b10 ;
b1 R
b11 *
1%
#40000
0%
#45000
b11 4
b11 ;
b10 R
1%
#50000
0%
#55000
b100 4
b100 ;
b11 R
1%
#60000
0%
#65000
b101 4
b101 ;
b100 R
1%
#70000
0%
#75000
b110 4
b110 ;
b101 R
1%
#80000
0%
#85000
b111 4
b111 ;
b110 R
1%
#90000
0%
#95000
b1000 4
b1000 ;
b111 R
1%
#100000
0%
#105000
b1001 4
b1001 ;
b1000 R
1%
#110000
0%
#115000
b100 @
b100 A
1:
18
1<
b0 4
b1010 ;
b1001 R
1%
#120000
0%
#125000
b101 K
b11 F
b11001 !
b11001 9
b1100110 >
b101 =
b11 "
b11 ?
0I
b1 4
b11 C
1/
0-
b101 G
b101 `
1g
b11 H
b11 m
1.
0T
0U
0V
1f
0:
08
0<
b100 P
b100 #
b100 5
b100 O
b100 S
b100 a
b1 ;
b0 R
1%
#130000
0%
#135000
b10 4
b10 ;
b1 R
b100 *
1%
#140000
0%
#145000
b11 4
b11 ;
b10 R
1%
#150000
0%
#155000
b100 4
b100 ;
b11 R
1%
#160000
0%
#165000
b101 4
b101 ;
b100 R
1%
#170000
0%
#175000
b110 4
b110 ;
b101 R
1%
#180000
0%
#185000
b111 4
b111 ;
b110 R
1%
#190000
0%
#195000
b1000 4
b1000 ;
b111 R
1%
#200000
0%
#205000
b1001 4
b1001 ;
b1000 R
1%
#210000
0%
#215000
b101 A
b11 @
1:
18
1<
b0 4
b1010 ;
b1001 R
1%
#220000
0%
#225000
b110 K
b10 F
b10000 !
b10000 9
b1101111 >
b110 =
b11 "
b11 ?
b1 4
0/
b10 C
00
b110 G
b110 `
b100 H
b100 m
0g
0.
1T
0f
0:
08
0<
b11 P
b101 #
b101 5
b101 O
b101 S
b101 a
b1 ;
b0 R
1%
#230000
0%
#235000
b10 4
b10 ;
b1 R
b101 *
1%
#240000
0%
#245000
b11 4
b11 ;
b10 R
1%
#250000
0%
#255000
b100 4
b100 ;
b11 R
1%
#260000
0%
#265000
b101 4
b101 ;
b100 R
1%
#270000
0%
#275000
b110 4
b110 ;
b101 R
1%
#280000
0%
#285000
b111 4
b111 ;
b110 R
1%
#290000
0%
#295000
b1000 4
b1000 ;
b111 R
1%
#300000
0%
#305000
b1001 4
b1001 ;
b1000 R
1%
#310000
0%
#315000
b10 @
b110 A
1:
18
1<
b0 4
b1010 ;
b1001 R
1%
#320000
0%
#325000
b111 K
b1 F
b10 !
b10 9
b1111101 >
b111 =
b10 "
b10 ?
b1 4
b1 C
b111 G
b111 `
0V
b101 H
b101 m
1.
0T
0U
1f
0:
08
0<
b10 P
b110 #
b110 5
b110 O
b110 S
b110 a
b1 ;
b0 R
1%
#330000
0%
#335000
b10 4
b10 ;
b1 R
b110 *
1%
#340000
0%
#345000
b11 4
b11 ;
b10 R
1%
#350000
0%
#355000
b100 4
b100 ;
b11 R
1%
#360000
0%
#365000
b101 4
b101 ;
b100 R
1%
#370000
0%
#375000
b110 4
b110 ;
b101 R
1%
#380000
0%
#385000
b111 4
b111 ;
b110 R
1%
#390000
0%
#395000
b1000 4
b1000 ;
b111 R
1%
#400000
0%
#405000
b1001 4
b1001 ;
b1000 R
1%
#410000
0%
#415000
b111 A
b1 @
1:
18
1<
b0 4
b1010 ;
b1001 R
1%
#420000
0%
#425000
b1000 K
b0 F
b1111000 !
b1111000 9
b1000 =
b111 >
b1 "
b1 ?
1V
b1 4
b0 C
b1000 G
b1000 `
1U
b110 H
b110 m
0.
1T
0f
0:
08
0<
b1 P
b111 #
b111 5
b111 O
b111 S
b111 a
b1 ;
b0 R
1%
#430000
0%
#435000
b10 4
b10 ;
b1 R
b111 *
1%
#440000
0%
#445000
b11 4
b11 ;
b10 R
1%
#450000
0%
#455000
b100 4
b100 ;
b11 R
1%
#460000
0%
#465000
b101 4
b101 ;
b100 R
1%
#470000
0%
#475000
b110 4
b110 ;
b101 R
1%
#480000
0%
#485000
b111 4
b111 ;
b110 R
1%
#490000
0%
